Metadata-Version: 1.1
Name: pascal-tokenizer
Version: 1.0.3
Summary: UNKNOWN
Home-page: UNKNOWN
Author: Artem Gavrilov
Author-email: info@teamfnd.ru
License: UNKNOWN
Platform: UNKNOWN
Classifier: Development Status :: 5 - Production/Stable
Classifier: Intended Audience :: Developers
Classifier: License :: OSI Approved :: Mozilla Public License 2.0 (MPL 2.0)
Classifier: Programming Language :: Python
Classifier: Topic :: Software Development :: Libraries :: Python Modules
